funcn-0.1.0.dist-info/licenses/LICENSE
funcn_cli/__init__.py
funcn_cli/config_manager.py
funcn_cli/main.py
funcn_cli/commands/__init__.py
funcn_cli/commands/add.py
funcn_cli/commands/build_cmd.py
funcn_cli/commands/init_cmd.py
funcn_cli/commands/list_components.py
funcn_cli/commands/mcp_cmd.py
funcn_cli/commands/search.py
funcn_cli/commands/source.py
funcn_cli/core/__init__.py
funcn_cli/core/component_manager.py
funcn_cli/core/known_llms.json
funcn_cli/core/models.py
funcn_cli/core/registry_handler.py
funcn-0.1.0.dist-info/METADATA
funcn-0.1.0.dist-info/WHEEL
funcn-0.1.0.dist-info/entry_points.txt
funcn-0.1.0.dist-info/top_level.txt
funcn-0.1.0.dist-info/RECORD
